mdsyntax/__init__.py
mdsyntax/cli.py
mdsyntax/py.typed
mdsyntax/renderer.py
mdsyntax-0.2.0.dist-info/METADATA
mdsyntax-0.2.0.dist-info/WHEEL
mdsyntax-0.2.0.dist-info/entry_points.txt
mdsyntax-0.2.0.dist-info/licenses/LICENSE
mdsyntax-0.2.0.dist-info/RECORD
