Metadata-Version: 2.4
Name: mdsyntax
Version: 0.2.0
Summary: Render markdown with syntax highlighting in the terminal
Project-URL: Homepage, https://github.com/yourusername/mdsyntax
Project-URL: Repository, https://github.com/yourusername/mdsyntax
Project-URL: Issues, https://github.com/yourusername/mdsyntax/issues
Author-email: Your Name <you@example.com>
License-Expression: MIT
License-File: LICENSE
Keywords: ansi,cli,console,markdown,syntax-highlighting,terminal
Classifier: Development Status :: 4 - Beta
Classifier: Environment :: Console
Classifier: Intended Audience :: Developers
Classifier: License :: OSI Approved :: MIT License
Classifier: Operating System :: OS Independent
Classifier: Programming Language :: Python :: 3
Classifier: Programming Language :: Python :: 3.10
Classifier: Programming Language :: Python :: 3.11
Classifier: Programming Language :: Python :: 3.12
Classifier: Programming Language :: Python :: 3.13
Classifier: Topic :: Terminals
Classifier: Topic :: Text Processing :: Markup :: Markdown
Classifier: Typing :: Typed
Requires-Python: >=3.10
Requires-Dist: colorama>=0.4.6
Requires-Dist: pygments>=2.17.0
Provides-Extra: dev
Requires-Dist: build; extra == 'dev'
Requires-Dist: pytest>=8.0; extra == 'dev'
Requires-Dist: ruff>=0.4; extra == 'dev'
Requires-Dist: twine; extra == 'dev'
